.DS_Store
nullsweep/__init__.py
nullsweep/api.py
nullsweep/config.py
nullsweep/router.py
nullsweep/bases/__init__.py
nullsweep/bases/handler.py
nullsweep/deletion/__init__.py
nullsweep/deletion/column.py
nullsweep/deletion/factory.py
nullsweep/deletion/listwise.py
nullsweep/deletion/dask_engine/__init__.py
nullsweep/deletion/dask_engine/column.py
nullsweep/deletion/dask_engine/listwise.py
nullsweep/deletion/pandas_engine/__init__.py
nullsweep/deletion/pandas_engine/column.py
nullsweep/deletion/pandas_engine/listwise.py
nullsweep/deletion/polars_engine/__init__.py
nullsweep/deletion/polars_engine/column.py
nullsweep/deletion/polars_engine/listwise.py
nullsweep/deletion/spark_engine/__init__.py
nullsweep/deletion/spark_engine/column.py
nullsweep/deletion/spark_engine/listwise.py
nullsweep/flag/__init__.py
nullsweep/flag/factory.py
nullsweep/flag/indicator.py
nullsweep/flag/dask_engine/__init__.py
nullsweep/flag/dask_engine/indicator.py
nullsweep/flag/pandas_engine/__init__.py
nullsweep/flag/pandas_engine/indicator.py
nullsweep/flag/polars_engine/__init__.py
nullsweep/flag/polars_engine/indicator.py
nullsweep/flag/spark_engine/__init__.py
nullsweep/flag/spark_engine/indicator.py
nullsweep/implementations/__init__.py
nullsweep/implementations/polars_simple_imputer.py
nullsweep/impute/__init__.py
nullsweep/impute/multi/__init__.py
nullsweep/impute/multi/knn.py
nullsweep/impute/multi/mice.py
nullsweep/impute/multi/regression.py
nullsweep/impute/multi/knn/__init__.py
nullsweep/impute/multi/knn/factory.py
nullsweep/impute/multi/knn/pandas_engine/__init__.py
nullsweep/impute/multi/knn/pandas_engine/knn.py
nullsweep/impute/multi/mice/__init__.py
nullsweep/impute/multi/mice/factory.py
nullsweep/impute/multi/mice/pandas_engine/__init__.py
nullsweep/impute/multi/mice/pandas_engine/mice.py
nullsweep/impute/multi/regression/__init__.py
nullsweep/impute/multi/regression/factory.py
nullsweep/impute/multi/regression/dask_engine/__init__.py
nullsweep-0.6.0.dist-info/LICENCE.md
nullsweep-0.6.0.dist-info/METADATA
nullsweep-0.6.0.dist-info/WHEEL
nullsweep-0.6.0.dist-info/top_level.txt
nullsweep-0.6.0.dist-info/RECORD
