Metadata-Version: 2.1
Name: nullsweep
Version: 0.6.0
Summary: A comprehensive Python package for managing and analyzing missing data in pandas DataFrames, starting with detection and expanding to complete handling.
Home-page: https://github.com/okanyenigun/nullsweep
Author: Okan Yenigün
Author-email: okanyenigun@gmail.com
License: MIT
Classifier: Development Status :: 3 - Alpha
Classifier: Intended Audience :: Developers
Classifier: Intended Audience :: Science/Research
Classifier: Topic :: Software Development :: Libraries :: Python Modules
Classifier: Topic :: Scientific/Engineering :: Mathematics
Classifier: License :: OSI Approved :: MIT License
Classifier: Programming Language :: Python :: 3
Classifier: Programming Language :: Python :: 3.7
Classifier: Programming Language :: Python :: 3.8
Classifier: Programming Language :: Python :: 3.9
Classifier: Programming Language :: Python :: 3.10
Classifier: Programming Language :: Python :: 3.11
Classifier: Operating System :: OS Independent
Requires-Python: >=3.7
License-File: LICENCE.md
Requires-Dist: pandas==2.2.2
Requires-Dist: scipy==1.13.1
Requires-Dist: statsmodels==0.14.2
Requires-Dist: scikit-learn==1.6.1
Requires-Dist: seaborn==0.13.2
Requires-Dist: missingno==0.5.2
Requires-Dist: upsetplot==0.9.0
Requires-Dist: wordcloud==1.9.4
Requires-Dist: polars==1.23.0
Requires-Dist: pyarrow==19.0.1
Requires-Dist: dask==2025.4.1
Requires-Dist: fsspec==2025.3.2
Requires-Dist: locket==1.0.0
Requires-Dist: partd==1.4.2
Requires-Dist: pyyaml==6.0.2
Requires-Dist: toolz==1.0.0
Requires-Dist: jinja2==3.1.6
Requires-Dist: dask-ml==2025.1.0
Provides-Extra: dev
Requires-Dist: twine==5.1.1; extra == "dev"
Provides-Extra: test
Requires-Dist: pytest==8.2.2; extra == "test"
